{"termTheme":"dark","layouts":{"layout-1":{"data":{"layout-restorer:data":{"main":{"dock":{"type":"split-area","orientation":"horizontal","children":[{"type":"tab-area","widgets":["notebook:Guide.ipynb"],"currentIndex":0},{"type":"split-area","orientation":"vertical","children":[{"type":"tab-area","widgets":["editor:src/index.ts"],"currentIndex":0},{"type":"tab-area","widgets":["terminal:1"],"currentIndex":0}],"sizes":[0.6027020135757418,0.39729798642425823]}],"sizes":[0.5177725874321045,0.48222741256789553]}}}}}}}